{
 "age": "10",
 "city": "BONJOUR",
 "name": "bonjour"
}
{
 "age": "30",
 "name": "John"
}
{
 "age": "30",
 "nname": "John"
}
{
 "age": "30",
 "nname": "John"
}
{
 "age": "30",
 "nname": "John"
}
{
 "age": "32",
 "city": "sdad",
 "name": "dfaf"
}
{
 "age": "30",
 "nname": "John"
}
{
 "age": "30",
 "nname": "John"
}
{
 "age": "30",
 "nname": "John"
}
{
 "age": "21",
 "city": "dsa",
 "name": "fdas"
}
{
 "age": "30",
 "nname": "John"
}
{
 "age": "11",
 "city": "dsad",
 "name": "dsadsa"
}
{
 "key1": "value1",
 "key2": "value%26"
}
{
 "age": "21",
 "city": "xsad",
 "name": "sad"
}
{
 "age": "21",
 "city": "dsa",
 "name": "fsa"
}
{
 "age": "21",
 "city": "dsad",
 "name": "smai"
}
{
 "key1": "value1",
 "key2": "value%26"
}
{
 "age": "30",
 "nname": "John"
}
{
 "name": "John"
}
{
 "age": "21",
 "city": "dsadadsa",
 "name": "dasdsa"
}
